nonebot_plugin_gocqhttp_cross_machine_upload_file/__init__.py
nonebot_plugin_gocqhttp_cross_machine_upload_file/config.py
nonebot_plugin_gocqhttp_cross_machine_upload_file/errors.py
nonebot_plugin_gocqhttp_cross_machine_upload_file/file_manager.py
nonebot_plugin_gocqhttp_cross_machine_upload_file-0.1.5.dist-info/METADATA
nonebot_plugin_gocqhttp_cross_machine_upload_file-0.1.5.dist-info/WHEEL
nonebot_plugin_gocqhttp_cross_machine_upload_file-0.1.5.dist-info/RECORD
